ZMS-5.1.0-py3.6-nspkg.pth
Products/zms/IZMSActionListContributor.py
Products/zms/IZMSCatalogAdapter.py
Products/zms/IZMSCatalogConnector.py
Products/zms/IZMSConfigurationProvider.py
Products/zms/IZMSDaemon.py
Products/zms/IZMSFormatProvider.py
Products/zms/IZMSLocale.py
Products/zms/IZMSMetacmdProvider.py
Products/zms/IZMSMetamodelProvider.py
Products/zms/IZMSRepositoryManager.py
Products/zms/IZMSRepositoryProvider.py
Products/zms/IZMSWorkflowProvider.py
Products/zms/ZMSCharformatManager.py
Products/zms/ZMSFilterManager.py
Products/zms/ZMSFormatProvider.py
Products/zms/ZMSFormatProviderAcquired.py
Products/zms/ZMSItem.py
Products/zms/ZMSMetacmdProvider.py
Products/zms/ZMSMetacmdProviderAcquired.py
Products/zms/ZMSMetadictManager.py
Products/zms/ZMSMetamodelProvider.py
Products/zms/ZMSMetaobjManager.py
Products/zms/ZMSRepositoryManager.py
Products/zms/ZMSTextformat.py
Products/zms/ZMSTextformatManager.py
Products/zms/ZMSWorkflowActivitiesManager.py
Products/zms/ZMSWorkflowItem.py
Products/zms/ZMSWorkflowProvider.py
Products/zms/ZMSWorkflowProviderAcquired.py
Products/zms/ZMSWorkflowTransitionsManager.py
Products/zms/ZMSZCatalogAdapter.py
Products/zms/ZMSZCatalogConnector.py
Products/zms/ZMSZCatalogSolrConnector.py
Products/zms/__init__.py
Products/zms/_accessmanager.py
Products/zms/_blobfields.py
Products/zms/_builder.py
Products/zms/_cachemanager.py
Products/zms/_confmanager.py
Products/zms/_copysupport.py
Products/zms/_deprecatedapi.py
Products/zms/_enummanager.py
Products/zms/_exportable.py
Products/zms/_fileutil.py
Products/zms/_filtermanager.py
Products/zms/_globals.py
Products/zms/_importable.py
Products/zms/_mediadb.py
Products/zms/_mimetypes.py
Products/zms/_multilangmanager.py
Products/zms/_objattrs.py
Products/zms/_objchildren.py
Products/zms/_objinputs.py
Products/zms/_objtypes.py
Products/zms/_pathhandler.py
Products/zms/_repositoryutil.py
Products/zms/_sequence.py
Products/zms/_textformatmanager.py
Products/zms/_versionmanager.py
Products/zms/_xmllib.py
ZMS-5.1.0.dist-info/AUTHORS
ZMS-5.1.0.dist-info/METADATA
ZMS-5.1.0.dist-info/WHEEL
ZMS-5.1.0.dist-info/namespace_packages.txt
ZMS-5.1.0.dist-info/top_level.txt
ZMS-5.1.0.dist-info/RECORD
