Metadata-Version: 2.1
Name: ZMS
Version: 5.1.0
Summary: ZMS: Simplified Content Modelling
Home-page: https://www.zms-publishing.com
Author: HOFFMANN+LIEBENBERG in association with SNTL Publishing, Berlin
Author-email: zms@sntl-publishing.com
License: UNKNOWN
Download-URL: https://github.com/zms-publishing/ZMS
Platform: UNKNOWN
Classifier: Development Status :: 5 - Production/Stable
Classifier: Framework :: Zope :: 5
Classifier: Programming Language :: Python :: 3
Classifier: Operating System :: OS Independent
Classifier: Environment :: Web Environment
Classifier: Topic :: Internet :: WWW/HTTP :: Site Management
Classifier: Topic :: Internet :: WWW/HTTP :: Dynamic Content
Classifier: Intended Audience :: Education
Classifier: Intended Audience :: Science/Research
Classifier: Intended Audience :: Customer Service
Classifier: Intended Audience :: End Users/Desktop
Classifier: Intended Audience :: Healthcare Industry
Classifier: Intended Audience :: Information Technology
Classifier: Intended Audience :: Telecommunications Industry
Classifier: Intended Audience :: Financial and Insurance Industry
Classifier: License :: OSI Approved :: GNU General Public License (GPL)
License-File: AUTHORS
Requires-Dist: docutils
Requires-Dist: configparser
Requires-Dist: Zope[wsgi]
Requires-Dist: Products.GenericSetup
Requires-Dist: Products.MailHost
Requires-Dist: Products.ExternalMethod
Requires-Dist: Products.CMFCore
Requires-Dist: Products.PythonScripts
Requires-Dist: Products.SiteErrorLog
Requires-Dist: Products.StandardCacheManagers
Requires-Dist: Products.Sessions
Requires-Dist: Products.TemporaryFolder
Requires-Dist: zope.app.publication
Requires-Dist: zope.authentication
Requires-Dist: zope.untrustedpython
Requires-Dist: zope.error
Requires-Dist: ZopeUndo
Requires-Dist: Pillow
Provides-Extra: zeo
Requires-Dist: ZEO ; extra == 'zeo'
Requires-Dist: Products.mcdutils ; extra == 'zeo'
